rshare-0.1.37.dist-info/METADATA
rshare-0.1.37.dist-info/WHEEL
rshare/fetch.py
rshare/py.typed
rshare/rshare.pyi
rshare/tests/main.py
rshare/utils/_rshare_version.py
rshare/__init__.py
rshare/rshare.pyd
rshare-0.1.37.dist-info/RECORD
