Metadata-Version: 2.3
Name: rshare
Version: 0.1.37
Classifier: Development Status :: 5 - Production/Stable
Classifier: Environment :: Console
Classifier: Intended Audience :: Developers
Classifier: License :: OSI Approved :: MIT License
Classifier: Operating System :: OS Independent
Classifier: Programming Language :: Python
Classifier: Programming Language :: Python :: 3 :: Only
Classifier: Programming Language :: Rust
Classifier: Topic :: Software Development :: Libraries :: Python Modules
Classifier: Topic :: Software Development :: Quality Assurance
Requires-Dist: akshare
Requires-Dist: requests
Requires-Dist: beautifulsoup4
Summary: It is a toy project for Python and Rust!
Keywords: python,rust,data,finance
Author: Albert King
Author-email: albertandking@gmail.com
License: MIT
Requires-Python: >=3.8
Project-URL: homepage, https://github.com/albertandking/rshare
Project-URL: documentation, https://rshare.readthedocs.io/
Project-URL: repository, https://github.com/albertandking/rshare
Project-URL: changelog, https://github.com/albertandking/rshare/blob/master/CHANGELOG.md
